pystackql/__init__.py
pystackql/errors.yaml
pystackql/magic.py
pystackql/magics.py
pystackql/core/__init__.py
pystackql/core/binary.py
pystackql/core/error_detector.py
pystackql/core/output.py
pystackql/core/query.py
pystackql/core/server.py
pystackql/core/stackql.py
pystackql/magic_ext/__init__.py
pystackql/magic_ext/base.py
pystackql/magic_ext/local.py
pystackql/magic_ext/server.py
pystackql/utils/__init__.py
pystackql/utils/auth.py
pystackql/utils/binary.py
pystackql/utils/download.py
pystackql/utils/helpers.py
pystackql/utils/package.py
pystackql/utils/params.py
pystackql/utils/platform.py
pystackql-3.8.2.dist-info/licenses/LICENSE
pystackql-3.8.2.dist-info/METADATA
pystackql-3.8.2.dist-info/WHEEL
pystackql-3.8.2.dist-info/top_level.txt
pystackql-3.8.2.dist-info/RECORD
