Metadata-Version: 2.4
Name: pystackql
Version: 3.8.2
Summary: A Python interface for StackQL
Author-email: Jeffrey Aven <javen@stackql.io>
License-Expression: MIT
Project-URL: Homepage, https://github.com/stackql/pystackql
Project-URL: Documentation, https://pystackql.readthedocs.io
Classifier: Operating System :: Microsoft :: Windows
Classifier: Operating System :: MacOS
Classifier: Operating System :: POSIX :: Linux
Classifier: Programming Language :: Python :: 3.9
Classifier: Programming Language :: Python :: 3.10
Classifier: Programming Language :: Python :: 3.11
Classifier: Programming Language :: Python :: 3.12
Classifier: Programming Language :: Python :: 3.13
Requires-Python: >=3.9
License-File: LICENSE
Requires-Dist: requests
Requires-Dist: pandas
Requires-Dist: IPython
Requires-Dist: psycopg[binary]>=3.1.0
Requires-Dist: nest-asyncio>=1.5.5
Requires-Dist: termcolor>=1.1.0
Requires-Dist: tqdm>=4.61.0
Requires-Dist: PyYAML>=5.4.0
Dynamic: license-file
